CHANGELOG.rst
CONTRIBUTING.rst
LICENSE
MANIFEST.in
README.rst
setup.cfg
setup.py
gearthonic/__init__.py
gearthonic/client.py
gearthonic/exceptions.py
gearthonic/methods.py
gearthonic/protocols.py
gearthonic.egg-info/PKG-INFO
gearthonic.egg-info/SOURCES.txt
gearthonic.egg-info/dependency_links.txt
gearthonic.egg-info/not-zip-safe
gearthonic.egg-info/requires.txt
gearthonic.egg-info/top_level.txt
test/test_client.py
test/test_collections.py
test/test_protocols.py