Metadata-Version: 1.1
Name: gearthonic
Version: 0.2.0
Summary: A simple client to the XML RPC API of Homegear.
Home-page: https://gitlab.com/wumpitz/gearthonic
Author: Timo Steidle
Author-email: mumpitz@wumpitz.de
License: MIT
Keywords: gearthonic
Platform: UNKNOWN
Classifier: Development Status :: 2 - Pre-Alpha
Classifier: Intended Audience :: Developers
Classifier: License :: OSI Approved :: MIT License
Classifier: Natural Language :: English
Classifier: Programming Language :: Python :: 2
Classifier: Programming Language :: Python :: 2.7
Classifier: Programming Language :: Python :: 3
Classifier: Programming Language :: Python :: 3.5
Classifier: Programming Language :: Python :: Implementation :: PyPy
